MANIFEST.in
README.rst
ez_setup.py
setup.cfg
setup.py
zbg/__init__.py
zbg.egg-info/PKG-INFO
zbg.egg-info/SOURCES.txt
zbg.egg-info/dependency_links.txt
zbg.egg-info/top_level.txt